[
    {
        "col": "col-6",
        "type": "text",
        "icon": "fa-font",
        "label": "Cognome",
        "description": "Inserisci testo",
        "placeholder": "Cognome del richiedente",
        "className": "form-control",
        "subtype": "text",
        "regex": "",
        "handle": true,
        "name": "cognome",
        "toggle": false,
        "required": true
    },
    {
        "col": "col-6",
        "type": "text",
        "icon": "fa-font",
        "label": "Nome",
        "description": "Inserisci testo",
        "placeholder": "Nome del richiedente",
        "className": "form-control",
        "subtype": "text",
        "regex": "",
        "handle": true,
        "name": "nome",
        "toggle": false,
        "required": true
    },
    {
        "col": "col-6",
        "type": "text",
        "icon": "fa-font",
        "label": "Nato/a a",
        "description": "Inserisci testo",
        "placeholder": "Città di nascita",
        "className": "form-control",
        "subtype": "text",
        "regex": "",
        "handle": true,
        "name": "citta-nascita",
        "toggle": false,
        "required": true
    },
    {
        "col": "col-6",
        "type": "date",
        "icon": "fa-calendar",
        "label": "Data di nascita",
        "placeholder": "Data",
        "className": "form-control",
        "name": "data-nascita",
        "toggle": false,
        "required": true
    },
    {
        "col": "col-12",
        "type": "text",
        "icon": "fa-font",
        "label": "Residente a",
        "description": "Inserisci testo",
        "placeholder": "Indirizzo e numero civico di residenza",
        "className": "form-control",
        "subtype": "text",
        "regex": "",
        "handle": true,
        "name": "residenza",
        "toggle": false,
        "required": true
    },
    {
        "type": "paragraph",
        "icon": "fa-paragraph",
        "label": "Testo statico",
        "placeholder": "in riferimento all'avviso pubblicato in data 30 Ottobre 2023",
        "name": "paragraph-1698746958219",
        "toggle": false
    },
    {
        "type": "paragraph",
        "icon": "fa-paragraph",
        "label": "Testo statico",
        "placeholder": "CHIEDE",
        "name": "paragraph-1682581961255",
        "toggle": false,
        "col": "col-12"
    },
    {
        "type": "paragraph",
        "icon": "fa-paragraph",
        "label": "Testo statico",
        "placeholder": "di essere iscritto/a nell’elenco delle persone idonee all’ufficio di Scrutatore di seggio elettorale previsto dall'art.9 della legge 30 Aprile 1999, n. 120.",
        "name": "paragraph-1682581974924",
        "toggle": false,
        "col": "col-12"
    },
    {
        "col": "col-12",
        "type": "paragraph",
        "icon": "fa-paragraph",
        "label": "DICHIARA",
        "placeholder": "A tale fine, il/la sottoscritto/a a norma degli artt. 46 e 47 del D.P.R. 445/2000, dichiara:",
        "name": "paragraph-1603704155009",
        "toggle": false
    },
    {
        "type": "paragraph",
        "icon": "fa-paragraph",
        "label": "Testo statico",
        "placeholder": "- di essere iscritto/a nelle liste elettorali del Comune di Catania;",
        "name": "paragraph-1682582172319",
        "toggle": false,
        "col": "col-12"
    },
    {
        "type": "paragraph",
        "icon": "fa-paragraph",
        "label": "Testo statico",
        "placeholder": "- di avere assolto gli obblighi scolastici;",
        "name": "paragraph-1682582205255",
        "toggle": false,
        "col": "col-12"
    },
    {
        "type": "paragraph",
        "icon": "fa-paragraph",
        "label": "Testo statico",
        "placeholder": "- di essere in possesso del seguente titolo di studio:",
        "name": "paragraph-1683014625691",
        "toggle": false,
        "col": "col-12"
    },
    {
        "type": "paragraph",
        "icon": "fa-paragraph",
        "label": "Testo statico",
        "placeholder": "Licenza Media",
        "name": "paragraph-1698747380682",
        "toggle": false,
        "col": "col-2"
    },
    {
        "type": "text",
        "icon": "fa-font",
        "label": "conseguita presso:",
        "description": "Inserisci testo",
        "placeholder": "Inserire il nome dell'istituto scolastico",
        "className": "form-control",
        "subtype": "text",
        "regex": "",
        "handle": true,
        "name": "lm-scuola",
        "toggle": false,
        "col": "col-7"
    },
    {
        "type": "text",
        "icon": "fa-font",
        "label": "nell'anno",
        "description": "Inserisci testo",
        "placeholder": "Inserire l'anno di conseguimento",
        "className": "form-control",
        "subtype": "text",
        "regex": "",
        "handle": true,
        "name": "lm-anno",
        "toggle": false,
        "col": "col-3"
    },
    {
        "type": "paragraph",
        "icon": "fa-paragraph",
        "label": "Testo statico",
        "placeholder": "Diploma",
        "name": "paragraph-1698747524289",
        "toggle": false,
        "col": "col-2"
    },
    {
        "type": "text",
        "icon": "fa-font",
        "label": "conseguito presso:",
        "description": "Inserisci testo",
        "placeholder": "Inserire il nome dell'istituto",
        "className": "form-control",
        "subtype": "text",
        "regex": "",
        "handle": true,
        "name": "dip-scuola",
        "toggle": false,
        "col": "col-7"
    },
    {
        "type": "text",
        "icon": "fa-font",
        "label": "nell'anno",
        "description": "Inserisci testo",
        "placeholder": "Inserire l'anno di conseguimento",
        "className": "form-control",
        "subtype": "text",
        "regex": "[0-9]{4,4}",
        "handle": true,
        "name": "dip-anno",
        "toggle": false,
        "col": "col-3"
    },
    {
        "type": "paragraph",
        "icon": "fa-paragraph",
        "label": "Testo statico",
        "placeholder": "Laurea",
        "name": "paragraph-1698747756504",
        "toggle": false,
        "col": "col-2"
    },
    {
        "type": "text",
        "icon": "fa-font",
        "label": "conseguita presso la Facoltà",
        "description": "Inserisci testo",
        "placeholder": "Inserire la Facoltà",
        "className": "form-control",
        "subtype": "text",
        "regex": "",
        "handle": true,
        "name": "la-facolta",
        "toggle": false,
        "col": "col-7"
    },
    {
        "type": "text",
        "icon": "fa-font",
        "label": "nell'anno",
        "description": "Inserisci testo",
        "placeholder": "Inserire l'anno di conseguimento",
        "className": "form-control",
        "subtype": "text",
        "regex": "[0-9]{4,4}",
        "handle": true,
        "name": "la-anno",
        "toggle": false,
        "col": "col-3"
    },
    {
        "type": "paragraph",
        "icon": "fa-paragraph",
        "label": "Testo statico",
        "placeholder": "- di non appartenere ad una delle categorie indicate nell’art.38 del T.U. approvato con D.P.R. 16/5/60, n.570 e cioè:",
        "name": "paragraph-1698749256162",
        "toggle": false,
        "col": "col-12"
    },
    {
        "type": "paragraph",
        "icon": "fa-paragraph",
        "label": "Testo statico",
        "placeholder": "a) i dipendenti dei ministeri dell’Interno, delle Poste e Telecomunicazioni e dei Trasporti;",
        "name": "paragraph-1698749288890",
        "toggle": false,
        "col": "col-12"
    },
    {
        "type": "paragraph",
        "icon": "fa-paragraph",
        "label": "Testo statico",
        "placeholder": "b) gli appartenenti alle Forze Armate in servizio;",
        "name": "paragraph-1698749312835",
        "toggle": false,
        "col": "col-12"
    },
    {
        "type": "paragraph",
        "icon": "fa-paragraph",
        "label": "Testo statico",
        "placeholder": "c) i funzionari medici designati, dal Comitato di gestione dell’Unità Sanitaria Locale, al rilascio delle certificazioni in favore degli elettori fisicamente impediti, a norma dell’art.14, lett. q) della L.23/12/78, n.833;",
        "name": "paragraph-1698749338323",
        "toggle": false,
        "col": "col-12"
    },
    {
        "type": "paragraph",
        "icon": "fa-paragraph",
        "label": "Testo statico",
        "placeholder": "d) i segretari comunali ed i dipendenti dei comuni addetti o comandati a prestare servizio presso gli uffici elettorali comunali;",
        "name": "paragraph-1698749373754",
        "toggle": false,
        "col": "col-12"
    },
    {
        "type": "paragraph",
        "icon": "fa-paragraph",
        "label": "Testo statico",
        "placeholder": "e) i candidati alle elezioni per le quali si svolge la votazione.",
        "name": "paragraph-1698749396418",
        "toggle": false,
        "col": "col-12"
    }
]